bilibili_video_mcp/__init__.py
bilibili_video_mcp/bilibili_server.py
bilibili_video_mcp-0.1.0.dist-info/licenses/LICENSE
bilibili_video_mcp-0.1.0.dist-info/METADATA
bilibili_video_mcp-0.1.0.dist-info/WHEEL
bilibili_video_mcp-0.1.0.dist-info/entry_points.txt
bilibili_video_mcp-0.1.0.dist-info/top_level.txt
bilibili_video_mcp-0.1.0.dist-info/RECORD
