Metadata-Version: 2.4
Name: bilibili-video-mcp
Version: 0.1.0
Summary: MCP server for downloading and extracting content from Bilibili videos
Author-email: yzfly <yz.liu.me@gmail.com>
License-Expression: MIT
Project-URL: Homepage, https://github.com/yzfly/bilibili-video-mcp
Project-URL: Repository, https://github.com/yzfly/bilibili-video-mcp
Project-URL: Issues, https://github.com/yzfly/bilibili-video-mcp/issues
Keywords: mcp,bilibili,video,asr,subtitle,server
Classifier: Development Status :: 3 - Alpha
Classifier: Intended Audience :: Developers
Classifier: Operating System :: OS Independent
Classifier: Programming Language :: Python :: 3
Classifier: Programming Language :: Python :: 3.8
Classifier: Programming Language :: Python :: 3.9
Classifier: Programming Language :: Python :: 3.10
Classifier: Programming Language :: Python :: 3.11
Classifier: Programming Language :: Python :: 3.12
Classifier: Topic :: Software Development :: Libraries :: Python Modules
Classifier: Topic :: Multimedia :: Video
Classifier: Topic :: Communications :: Chat
Requires-Python: >=3.8
License-File: LICENSE
Requires-Dist: fastmcp>=2.0.0
Requires-Dist: requests>=2.25.0
Requires-Dist: ffmpeg-python>=0.2.0
Requires-Dist: tqdm>=4.60.0
Requires-Dist: openai>=1.0.0
Requires-Dist: you-get>=0.4.1650
Provides-Extra: dev
Requires-Dist: pytest>=7.0.0; extra == "dev"
Requires-Dist: pytest-asyncio>=0.21.0; extra == "dev"
Requires-Dist: black>=22.0.0; extra == "dev"
Requires-Dist: isort>=5.10.0; extra == "dev"
Requires-Dist: flake8>=4.0.0; extra == "dev"
Requires-Dist: mypy>=1.0.0; extra == "dev"
Dynamic: license-file
